platformshconfig/__init__.py
platformshconfig/config.py
platformshconfig-2.4.0.dist-info/LICENSE
platformshconfig-2.4.0.dist-info/METADATA
platformshconfig-2.4.0.dist-info/WHEEL
platformshconfig-2.4.0.dist-info/top_level.txt
platformshconfig-2.4.0.dist-info/RECORD
