Metadata-Version: 2.1
Name: platformshconfig
Version: 2.4.0
Summary: Small helper to access Platform.sh environment variables.
Home-page: https://github.com/platformsh/config-reader-python3
Author: Platform.sh
Author-email: sayhello@platform.sh
License: MIT
Platform: UNKNOWN
Classifier: Development Status :: 5 - Production/Stable
Classifier: License :: OSI Approved :: MIT License
Classifier: Natural Language :: English
Classifier: Operating System :: OS Independent
Classifier: Programming Language :: Python :: 3.5
Classifier: Programming Language :: Python :: 3.6
Classifier: Programming Language :: Python :: 3.7
Classifier: Programming Language :: Python :: 3 :: Only
